Cheetah_GH/__init__.py
Cheetah_GH/gh_and_py_runner.py
Cheetah_GH/helpers.py
Cheetah_GH/unittest_runner.py
cheetah_gh-0.1.10.dist-info/METADATA
cheetah_gh-0.1.10.dist-info/WHEEL
cheetah_gh-0.1.10.dist-info/entry_points.txt
cheetah_gh-0.1.10.dist-info/licenses/LICENSE.md
cheetah_gh-0.1.10.dist-info/RECORD
