Metadata-Version: 2.4
Name: Cheetah_GH
Version: 0.1.10
Summary: Runs Grasshopper components and stops Rhino from Python components. Optionally runs Rhino3D and Grasshopper from the command line.
Project-URL: Homepage, https://github.com/JamesParrott/Cheetah_GH
Project-URL: Bug Tracker, https://github.com/JamesParrott/Cheetah_GH/issues
Author-email: James Parrott <james.parrott@proton.me>
License: Copyright 2024 James Parrott
License-File: LICENSE.md
Keywords: Grasshopper,Rhino,components,control,runner,tests
Classifier: Programming Language :: Python
Requires-Python: >=2.7
